{
    "type": "FeatureCollection",
    "features": [{
            "type": "Feature",
            "properties": {},
            "geometry": {
                "type": "Polygon",
                "coordinates": [
                    [
                        [
                            108.8324761390686,
                            34.20885647953598
                        ],
                        [
                            108.83254051208496,
                            34.207880479126565
                        ],
                        [
                            108.83389234542847,
                            34.20786273355998
                        ],
                        [
                            108.83383870124817,
                            34.208758880003636
                        ],
                        [
                            108.8324761390686,
                            34.20885647953598
                        ]
                    ]
                ]
            }
        },
        {
            "type": "Feature",
            "properties": {},
            "geometry": {
                "type": "Polygon",
                "coordinates": [
                    [
                        [
                            108.83450388908386,
                            34.20872338923659
                        ],
                        [
                            108.83450388908386,
                            34.20820877143483
                        ],
                        [
                            108.83553385734558,
                            34.2082974988662
                        ],
                        [
                            108.83579134941101,
                            34.2087145165425
                        ],
                        [
                            108.83498668670654,
                            34.208936333614744
                        ],
                        [
                            108.83450388908386,
                            34.20872338923659
                        ]
                    ]
                ]
            }
        },
        {
            "type": "Feature",
            "properties": {},
            "geometry": {
                "type": "Polygon",
                "coordinates": [
                    [
                        [
                            108.83655309677123,
                            34.2088476068559
                        ],
                        [
                            108.83655309677123,
                            34.20816440768414
                        ],
                        [
                            108.83839845657349,
                            34.20820877143483
                        ],
                        [
                            108.83849501609802,
                            34.20883873417489
                        ],
                        [
                            108.83655309677123,
                            34.2088476068559
                        ]
                    ]
                ]
            }
        },
        {
            "type": "Feature",
            "properties": {},
            "geometry": {
                "type": "Polygon",
                "coordinates": [
                    [
                        [
                            108.83903145790099,
                            34.208820988810025
                        ],
                        [
                            108.83917093276978,
                            34.20786273355998
                        ],
                        [
                            108.83986830711365,
                            34.20794258858026
                        ],
                        [
                            108.83970737457275,
                            34.208758880003636
                        ],
                        [
                            108.83903145790099,
                            34.208820988810025
                        ]
                    ]
                ]
            }
        },
        {
            "type": "Feature",
            "properties": {},
            "geometry": {
                "type": "Polygon",
                "coordinates": [
                    [
                        [
                            108.83273363113403,
                            34.207374729014184
                        ],
                        [
                            108.83272290229797,
                            34.20614139584089
                        ],
                        [
                            108.83440732955933,
                            34.20629223611846
                        ],
                        [
                            108.8346219062805,
                            34.20738360184931
                        ],
                        [
                            108.83273363113403,
                            34.207374729014184
                        ]
                    ]
                ]
            }
        },
        {
            "type": "Feature",
            "properties": {},
            "geometry": {
                "type": "Polygon",
                "coordinates": [
                    [
                        [
                            108.83506178855896,
                            34.20729487345586
                        ],
                        [
                            108.83506178855896,
                            34.20729487345586
                        ],
                        [
                            108.83506178855896,
                            34.20729487345586
                        ],
                        [
                            108.83506178855896,
                            34.20729487345586
                        ]
                    ]
                ]
            }
        },
        {
            "type": "Feature",
            "properties": {},
            "geometry": {
                "type": "Polygon",
                "coordinates": [
                    [
                        [
                            108.8350510597229,
                            34.2072682549196
                        ],
                        [
                            108.83504033088684,
                            34.20665602626555
                        ],
                        [
                            108.83703589439392,
                            34.20660278878113
                        ],
                        [
                            108.83745431900024,
                            34.20741022034913
                        ],
                        [
                            108.8350510597229,
                            34.2072682549196
                        ]
                    ]
                ]
            }
        },
        {
            "type": "Feature",
            "properties": {},
            "geometry": {
                "type": "Polygon",
                "coordinates": [
                    [
                        [
                            108.83790493011473,
                            34.20745458449684
                        ],
                        [
                            108.83786201477051,
                            34.20647856785336
                        ],
                        [
                            108.83999705314636,
                            34.20656729710617
                        ],
                        [
                            108.84015798568726,
                            34.20754331272217
                        ],
                        [
                            108.83790493011473,
                            34.20745458449684
                        ]
                    ]
                ]
            }
        },
        {
            "type": "Feature",
            "properties": {},
            "geometry": {
                "type": "Polygon",
                "coordinates": [
                    [
                        [
                            108.83275508880615,
                            34.20536057126524
                        ],
                        [
                            108.83278727531432,
                            34.203967491274426
                        ],
                        [
                            108.83497595787048,
                            34.20414495497323
                        ],
                        [
                            108.83516907691956,
                            34.205271840742135
                        ],
                        [
                            108.83275508880615,
                            34.20536057126524
                        ]
                    ]
                ]
            }
        },
        {
            "type": "Feature",
            "properties": {},
            "geometry": {
                "type": "Polygon",
                "coordinates": [
                    [
                        [
                            108.83585572242737,
                            34.20503226786322
                        ],
                        [
                            108.83583426475525,
                            34.20434903776502
                        ],
                        [
                            108.8400936126709,
                            34.204641851342345
                        ],
                        [
                            108.8401472568512,
                            34.20556465111387
                        ],
                        [
                            108.83585572242737,
                            34.20503226786322
                        ]
                    ]
                ]
            }
        }
    ]
}